cfnresponse/__init__.py
cfnresponse2-1.0.7.dist-info/LICENSE
cfnresponse2-1.0.7.dist-info/METADATA
cfnresponse2-1.0.7.dist-info/WHEEL
cfnresponse2-1.0.7.dist-info/top_level.txt
cfnresponse2-1.0.7.dist-info/RECORD
