Metadata-Version: 2.1
Name: cfnresponse2
Version: 1.0.7
Summary: Send a response object to a custom resource by way of an Amazon S3 presigned URL
Home-page: https://github.com/ggiallo28/cfnresponse
Author: Amazon Web Services
Classifier: Programming Language :: Python :: 3
Classifier: Programming Language :: Python :: 2
Classifier: Development Status :: 5 - Production/Stable
Classifier: License :: OSI Approved :: Apache Software License
Classifier: Topic :: Software Development :: Libraries :: Python Modules
License-File: LICENSE
Requires-Dist: urllib3
